salt_sls/conf.py
salt_sls/scripts.py
salt_sls/version.py
salt_sls/salt_sls/init.py
salt_sls-1.0.1.dist-info/LICENSE
salt_sls-1.0.1.dist-info/METADATA
salt_sls-1.0.1.dist-info/WHEEL
salt_sls-1.0.1.dist-info/entry_points.txt
salt_sls-1.0.1.dist-info/top_level.txt
salt_sls-1.0.1.dist-info/RECORD
