Metadata-Version: 2.1
Name: salt-sls
Version: 1.0.1
Summary: Run single a Salt SLS file agentless locally.
Home-page: https://gitlab.com/vmware/pop/salt-sls
Author: Tyler Levy Conde
Author-email: tyjohnson@vmware.com
License: Apache Software License 2.0
Keywords: salt,SLS,agentless,masterless,minionless
Platform: UNKNOWN
Classifier: Environment :: Console
Classifier: Intended Audience :: Developers
Classifier: Intended Audience :: Information Technology
Classifier: Intended Audience :: System Administrators
Classifier: Operating System :: OS Independent
Classifier: Programming Language :: Python
Classifier: Programming Language :: Python :: 3.8
Classifier: Programming Language :: Python :: 3.9
Classifier: Programming Language :: Python :: 3.10
Classifier: Programming Language :: Python :: 3.11
Classifier: Development Status :: 5 - Production/Stable
Classifier: License :: OSI Approved :: Apache Software License
Requires-Python: >=3.8
License-File: LICENSE
Requires-Dist: pop >=23.0.0
Requires-Dist: salt
Provides-Extra: full
Requires-Dist: salt ; extra == 'full'
Provides-Extra: salt
Requires-Dist: salt ; extra == 'salt'
